{
  "dependencies": [
    {
      "name": "@commitlint/cli",
      "type": "build"
    },
    {
      "name": "@commitlint/config-conventional",
      "type": "build"
    },
    {
      "name": "@nrwl/cli",
      "type": "build"
    },
    {
      "name": "@nrwl/workspace",
      "type": "build"
    },
    {
      "name": "@types/node",
      "version": "^12",
      "type": "build"
    },
    {
      "name": "aws-prototyping-sdk",
      "type": "build"
    },
    {
      "name": "cz-conventional-changelog",
      "type": "build"
    },
    {
      "name": "husky",
      "type": "build"
    },
    {
      "name": "npm-check-updates",
      "version": "^12",
      "type": "build"
    },
    {
      "name": "prettier",
      "type": "build"
    },
    {
      "name": "projen",
      "type": "build"
    },
    {
      "name": "ts-node",
      "version": "^9",
      "type": "build"
    },
    {
      "name": "typescript",
      "type": "build"
    }
  ],
  "//": "~~ Generated by projen. To modify, edit .projenrc.js and run \"npx projen\"."
}
